Metadata-Version: 2.2
Name: cleanflo
Version: 0.1.0
Summary: A beginner-friendly Python package for easy data cleaning and preprocessing.
Home-page: https://github.com/yourusername/cleanflo
Author: MYNAMPATI SRI RANGANADHA AVIANSH
Author-email: aviinashhreddyy77@gmail.com
Keywords: data cleaning,preprocessing,data science,machine learning
Classifier: Programming Language :: Python :: 3
Classifier: License :: OSI Approved :: MIT License
Classifier: Operating System :: OS Independent
Classifier: Intended Audience :: Developers
Classifier: Intended Audience :: Education
Classifier: Topic :: Software Development :: Libraries :: Python Modules
Requires-Python: >=3.7
License-File: LICENSE
Requires-Dist: numpy
Requires-Dist: pandas
Requires-Dist: scikit-learn
Requires-Dist: matplotlib
Requires-Dist: seaborn
Requires-Dist: nltk
Dynamic: author
Dynamic: author-email
Dynamic: classifier
Dynamic: description
Dynamic: description-content-type
Dynamic: home-page
Dynamic: keywords
Dynamic: requires-dist
Dynamic: requires-python
Dynamic: summary
